[
    {
        "name": "Buy",
        "chest_unopened_img": "/images/items/close.png",
        "chest_opened_img": "/images/items/open.png",
        "overlay_background": "#000000",
        "access_rules": [
            " "
        ],
        "sections": [
            {
                "name": "Smoke Some Cigarettes",
                "access_rules": [],
                "visibility_rules": [],
                "item_count": 1
            },
            {
                "name": "Buy Ankh",
                "access_rules": [],
                "visibility_rules": [],
                "item_count": 1
            },
            {
                "name": "Buy Horseshoe",
                "access_rules": [],
                "visibility_rules": [],
                "item_count": 1
            },
            {
                "name": "Buy Golden Horseshoe",
                "access_rules": [],
                "visibility_rules": [],
                "item_count": 1
            },
            {
                "name": "Buy Hamsa",
                "access_rules": [],
                "visibility_rules": [],
                "item_count": 1
            },
            {
                "name": "Buy Rotated Hamsa",
                "access_rules": [],
                "visibility_rules": [],
                "item_count": 1
            },
            {
                "name": "Buy Lucky Cat",
                "access_rules": [],
                "visibility_rules": [],
                "item_count": 1
            },
            {
                "name": "Buy Chonky Cat",
                "access_rules": [],
                "visibility_rules": [],
                "item_count": 1
            },
            {
                "name": "Buy Swole Cat",
                "access_rules": [],
                "visibility_rules": [],
                "item_count": 1
            },
            {
                "name": "Buy One Trick Pony",
                "access_rules": [],
                "visibility_rules": [],
                "item_count": 1
            },
            {
                "name": "Buy Red Shiny Rock",
                "access_rules": [],
                "visibility_rules": [],
                "item_count": 1
            },
            {
                "name": "Buy Tarot Deck",
                "access_rules": [],
                "visibility_rules": [],
                "item_count": 1
            },
            {
                "name": "Buy Dung Beetle",
                "access_rules": [],
                "visibility_rules": [],
                "item_count": 1
            },
            {
                "name": "Buy Grandmas Purse",
                "access_rules": [],
                "visibility_rules": [],
                "item_count": 1
            },
            {
                "name": "Buy Pentacle",
                "access_rules": [],
                "visibility_rules": [],
                "item_count": 1
            },
            {
                "name": "Buy Property Certificate",
                "access_rules": [],
                "visibility_rules": [],
                "item_count": 1
            },
            {
                "name": "Buy Nuclear Button",
                "access_rules": [],
                "visibility_rules": [],
                "item_count": 1
            },
            {
                "name": "Buy Dear Diary",
                "access_rules": [],
                "visibility_rules": [],
                "item_count": 1
            },
            {
                "name": "Buy Megaphone",
                "access_rules": [],
                "visibility_rules": [],
                "item_count": 1
            },
            {
                "name": "Buy Super Capacitor",
                "access_rules": [],
                "visibility_rules": [],
                "item_count": 1
            },
            {
                "name": "Buy Dynamo",
                "access_rules": [],
                "visibility_rules": [],
                "item_count": 1
            },
            {
                "name": "Buy Scratch And Hope",
                "access_rules": [],
                "visibility_rules": [],
                "item_count": 1
            },
            {
                "name": "Buy Stonks",
                "access_rules": [],
                "visibility_rules": [],
                "item_count": 1
            },
            {
                "name": "Buy Car Battery",
                "access_rules": [],
                "visibility_rules": [],
                "item_count": 1
            },
            {
                "name": "Buy Expired Meds",
                "access_rules": [],
                "visibility_rules": [],
                "item_count": 1
            },
            {
                "name": "Buy Midas Touch",
                "access_rules": [],
                "visibility_rules": [],
                "item_count": 1
            },
            {
                "name": "Buy Number 1",
                "access_rules": [],
                "visibility_rules": [],
                "item_count": 1
            },
            {
                "name": "Buy Number 2",
                "access_rules": [],
                "visibility_rules": [],
                "item_count": 1
            },
            {
                "name": "Buy Pain Killers",
                "access_rules": [],
                "visibility_rules": [],
                "item_count": 1
            },
            {
                "name": "Buy Lost Wallet",
                "access_rules": [],
                "visibility_rules": [],
                "item_count": 1
            },
            {
                "name": "Buy Calendar",
                "access_rules": [],
                "visibility_rules": [],
                "item_count": 1
            },
            {
                "name": "Buy Little Star",
                "access_rules": [],
                "visibility_rules": [],
                "item_count": 1
            },
            {
                "name": "Buy Fortune Cookie",
                "access_rules": [],
                "visibility_rules": [],
                "item_count": 1
            },
            {
                "name": "Buy Fidelity Card",
                "access_rules": [],
                "visibility_rules": [],
                "item_count": 1
            },
            {
                "name": "Buy Sardines",
                "access_rules": [],
                "visibility_rules": [],
                "item_count": 1
            },
            {
                "name": "Buy Broken Calculator",
                "access_rules": [],
                "visibility_rules": [],
                "item_count": 1
            },
            {
                "name": "Buy The Collector",
                "access_rules": [],
                "visibility_rules": [],
                "item_count": 1
            },
            {
                "name": "Buy Channeler of Fortune",
                "access_rules": [],
                "visibility_rules": [],
                "item_count": 1
            },
            {
                "name": "Buy Nose",
                "access_rules": [],
                "visibility_rules": [],
                "item_count": 1
            },
            {
                "name": "Buy Eye Jar",
                "access_rules": [],
                "visibility_rules": [],
                "item_count": 1
            },
            {
                "name": "Buy Voice Mail",
                "access_rules": [],
                "visibility_rules": [],
                "item_count": 1
            },
            {
                "name": "Buy Ring Bell",
                "access_rules": [],
                "visibility_rules": [],
                "item_count": 1
            },
            {
                "name": "Buy Consolation Prize",
                "access_rules": [],
                "visibility_rules": [],
                "item_count": 1
            },
            {
                "name": "Buy Dark Lotus",
                "access_rules": [],
                "visibility_rules": [],
                "item_count": 1
            },
            {
                "name": "Buy Weird Clock",
                "access_rules": [],
                "visibility_rules": [],
                "item_count": 1
            },
            {
                "name": "Buy Music Tape",
                "access_rules": [],
                "visibility_rules": [],
                "item_count": 1
            },
            {
                "name": "Buy Shopping Cart",
                "access_rules": [],
                "visibility_rules": [],
                "item_count": 1
            },
            {
                "name": "Buy Crowbar",
                "access_rules": [],
                "visibility_rules": [],
                "item_count": 1
            },
            {
                "name": "Buy Disc A",
                "access_rules": [],
                "visibility_rules": [],
                "item_count": 1
            },
            {
                "name": "Buy Disc B",
                "access_rules": [],
                "visibility_rules": [],
                "item_count": 1
            },
            {
                "name": "Buy Disc C",
                "access_rules": [],
                "visibility_rules": [],
                "item_count": 1
            },
            {
                "name": "Buy Cardboard House",
                "access_rules": [],
                "visibility_rules": [],
                "item_count": 1
            },
            {
                "name": "Buy Lost Briefcase",
                "access_rules": [],
                "visibility_rules": [],
                "item_count": 1
            },
            {
                "name": "Buy Electricity Meter",
                "access_rules": [],
                "visibility_rules": [],
                "item_count": 1
            },
            {
                "name": "Buy Potato Battery",
                "access_rules": [],
                "visibility_rules": [],
                "item_count": 1
            },
            {
                "name": "Buy Ancient Coin",
                "access_rules": [],
                "visibility_rules": [],
                "item_count": 1
            },
            {
                "name": "Buy Cat Food",
                "access_rules": [],
                "visibility_rules": [],
                "item_count": 1
            },
            {
                "name": "Buy Depression",
                "access_rules": [],
                "visibility_rules": [],
                "item_count": 1
            },
            {
                "name": "Buy Toy Train",
                "access_rules": [],
                "visibility_rules": [],
                "item_count": 1
            },
            {
                "name": "Buy Steam Locomotive",
                "access_rules": [],
                "visibility_rules": [],
                "item_count": 1
            },
            {
                "name": "Buy Diesel Locomotive",
                "access_rules": [],
                "visibility_rules": [],
                "item_count": 1
            },
            {
                "name": "Buy Clover Voucher",
                "access_rules": [],
                "visibility_rules": [],
                "item_count": 1
            },
            {
                "name": "Buy Clover Pot",
                "access_rules": [],
                "visibility_rules": [],
                "item_count": 1
            },
            {
                "name": "Buy Clover Pet",
                "access_rules": [],
                "visibility_rules": [],
                "item_count": 1
            },
            {
                "name": "Buy Clover Field",
                "access_rules": [],
                "visibility_rules": [],
                "item_count": 1
            },
            {
                "name": "Buy Mushrooms",
                "access_rules": [],
                "visibility_rules": [],
                "item_count": 1
            },
            {
                "name": "Buy Vines Soup",
                "access_rules": [],
                "visibility_rules": [],
                "item_count": 1
            },
            {
                "name": "Buy Very Big Mushroom",
                "access_rules": [],
                "visibility_rules": [],
                "item_count": 1
            },
            {
                "name": "Buy Abyssu",
                "access_rules": [],
                "visibility_rules": [],
                "item_count": 1
            },
            {
                "name": "Buy Vorago",
                "access_rules": [],
                "visibility_rules": [],
                "item_count": 1
            },
            {
                "name": "Buy Barathrum",
                "access_rules": [],
                "visibility_rules": [],
                "item_count": 1
            },
            {
                "name": "Buy Stain",
                "access_rules": [],
                "visibility_rules": [],
                "item_count": 1
            },
            {
                "name": "Buy Abstract Painting",
                "access_rules": [],
                "visibility_rules": [],
                "item_count": 1
            },
            {
                "name": "Buy Pareidolia",
                "access_rules": [],
                "visibility_rules": [],
                "item_count": 1
            },
            {
                "name": "Buy Hourglass",
                "access_rules": [],
                "visibility_rules": [],
                "item_count": 1
            },
            {
                "name": "Buy Fruit Basket",
                "access_rules": [],
                "visibility_rules": [],
                "item_count": 1
            },
            {
                "name": "Buy Seven Sins Stone",
                "access_rules": [],
                "visibility_rules": [],
                "item_count": 1
            },
            {
                "name": "Buy Necklace",
                "access_rules": [],
                "visibility_rules": [],
                "item_count": 1
            },
            {
                "name": "Buy Clover Bell",
                "access_rules": [],
                "visibility_rules": [],
                "item_count": 1
            },
            {
                "name": "Buy Red Pepper",
                "access_rules": [],
                "visibility_rules": [],
                "item_count": 1
            },
            {
                "name": "Buy Green Pepper",
                "access_rules": [],
                "visibility_rules": [],
                "item_count": 1
            },
            {
                "name": "Buy Rotten Pepper",
                "access_rules": [],
                "visibility_rules": [],
                "item_count": 1
            },
            {
                "name": "Buy Bell Pepper",
                "access_rules": [],
                "visibility_rules": [],
                "item_count": 1
            },
            {
                "name": "Buy Golden Pepper",
                "access_rules": [],
                "visibility_rules": [],
                "item_count": 1
            },
            {
                "name": "Buy Demons Horn",
                "access_rules": [],
                "visibility_rules": [],
                "item_count": 1
            },
            {
                "name": "Buy Necronomicon",
                "access_rules": [],
                "visibility_rules": [],
                "item_count": 1
            },
            {
                "name": "Buy Holy Bible",
                "access_rules": [],
                "visibility_rules": [],
                "item_count": 1
            },
            {
                "name": "Buy Baphomet",
                "access_rules": [],
                "visibility_rules": [],
                "item_count": 1
            },
            {
                "name": "Buy Cross",
                "access_rules": [],
                "visibility_rules": [],
                "item_count": 1
            },
            {
                "name": "Buy Rosary",
                "access_rules": [],
                "visibility_rules": [],
                "item_count": 1
            },
            {
                "name": "Buy Book Of Shadows",
                "access_rules": [],
                "visibility_rules": [],
                "item_count": 1
            },
            {
                "name": "Buy Gabihbbh",
                "access_rules": [],
                "visibility_rules": [],
                "item_count": 1
            },
            {
                "name": "Buy Possessed Cell Phone",
                "access_rules": [],
                "visibility_rules": [],
                "item_count": 1
            },
            {
                "name": "Buy Magical Tomato",
                "access_rules": [],
                "visibility_rules": [],
                "item_count": 1
            },
            {
                "name": "Buy Ritual Bell",
                "access_rules": [],
                "visibility_rules": [],
                "item_count": 1
            },
            {
                "name": "Buy Crystal Skull",
                "access_rules": [],
                "visibility_rules": [],
                "item_count": 1
            },
            {
                "name": "Buy Evil Deal",
                "access_rules": [],
                "visibility_rules": [],
                "item_count": 1
            },
            {
                "name": "Buy Chastity Belt",
                "access_rules": [],
                "visibility_rules": [],
                "item_count": 1
            },
            {
                "name": "Buy Photo Book",
                "access_rules": [],
                "visibility_rules": [],
                "item_count": 1
            },
            {
                "name": "Buy Lemon Picture",
                "access_rules": [],
                "visibility_rules": [],
                "item_count": 1
            },
            {
                "name": "Buy Cherry Picture",
                "access_rules": [],
                "visibility_rules": [],
                "item_count": 1
            },
            {
                "name": "Buy Clover Picture",
                "access_rules": [],
                "visibility_rules": [],
                "item_count": 1
            },
            {
                "name": "Buy Bell Picture",
                "access_rules": [],
                "visibility_rules": [],
                "item_count": 1
            },
            {
                "name": "Buy Diamond Picture",
                "access_rules": [],
                "visibility_rules": [],
                "item_count": 1
            },
            {
                "name": "Buy Treasure Picture",
                "access_rules": [],
                "visibility_rules": [],
                "item_count": 1
            },
            {
                "name": "Buy Seven Picture",
                "access_rules": [],
                "visibility_rules": [],
                "item_count": 1
            },
            {
                "name": "Buy Clicker",
                "access_rules": [],
                "visibility_rules": [],
                "item_count": 1
            },
            {
                "name": "Buy AA Batteries",
                "access_rules": [],
                "visibility_rules": [],
                "item_count": 1
            },
            {
                "name": "Buy Crystal Sphere",
                "access_rules": [],
                "visibility_rules": [],
                "item_count": 1
            },
            {
                "name": "Buy Naughty Dealer",
                "access_rules": [],
                "visibility_rules": [],
                "item_count": 1
            },
            {
                "name": "Buy Greedy King",
                "access_rules": [],
                "visibility_rules": [],
                "item_count": 1
            },
            {
                "name": "Buy Raging Capitalist",
                "access_rules": [],
                "visibility_rules": [],
                "item_count": 1
            },
            {
                "name": "Buy Personal Trainer",
                "access_rules": [],
                "visibility_rules": [],
                "item_count": 1
            },
            {
                "name": "Buy Electrician",
                "access_rules": [],
                "visibility_rules": [],
                "item_count": 1
            },
            {
                "name": "Buy Fortune Teller",
                "access_rules": [],
                "visibility_rules": [],
                "item_count": 1
            },
            {
                "name": "Buy Golden Lemon",
                "access_rules": [],
                "visibility_rules": [],
                "item_count": 1
            },
            {
                "name": "Buy Golden Cherry",
                "access_rules": [],
                "visibility_rules": [],
                "item_count": 1
            },
            {
                "name": "Buy Golden Clover",
                "access_rules": [],
                "visibility_rules": [],
                "item_count": 1
            },
            {
                "name": "Buy Golden Bell",
                "access_rules": [],
                "visibility_rules": [],
                "item_count": 1
            },
            {
                "name": "Buy Golden Diamond",
                "access_rules": [],
                "visibility_rules": [],
                "item_count": 1
            },
            {
                "name": "Buy Golden Treasure",
                "access_rules": [],
                "visibility_rules": [],
                "item_count": 1
            },
            {
                "name": "Buy Golden Seven",
                "access_rules": [],
                "visibility_rules": [],
                "item_count": 1
            },
            {
                "name": "Buy Bricks",
                "access_rules": [],
                "visibility_rules": [],
                "item_count": 1
            },
            {
                "name": "Buy Wood",
                "access_rules": [],
                "visibility_rules": [],
                "item_count": 1
            },
            {
                "name": "Buy Sheep",
                "access_rules": [],
                "visibility_rules": [],
                "item_count": 1
            },
            {
                "name": "Buy Wheat",
                "access_rules": [],
                "visibility_rules": [],
                "item_count": 1
            },
            {
                "name": "Buy Stone",
                "access_rules": [],
                "visibility_rules": [],
                "item_count": 1
            },
            {
                "name": "Buy Harbor",
                "access_rules": [],
                "visibility_rules": [],
                "item_count": 1
            },
            {
                "name": "Buy Thief",
                "access_rules": [],
                "visibility_rules": [],
                "item_count": 1
            },
            {
                "name": "Buy Wheelbarrow",
                "access_rules": [],
                "visibility_rules": [],
                "item_count": 1
            },
            {
                "name": "Buy Shoe",
                "access_rules": [],
                "visibility_rules": [],
                "item_count": 1
            },
            {
                "name": "Buy Thimble",
                "access_rules": [],
                "visibility_rules": [],
                "item_count": 1
            },
            {
                "name": "Buy Iron",
                "access_rules": [],
                "visibility_rules": [],
                "item_count": 1
            },
            {
                "name": "Buy Car",
                "access_rules": [],
                "visibility_rules": [],
                "item_count": 1
            },
            {
                "name": "Buy Ship",
                "access_rules": [],
                "visibility_rules": [],
                "item_count": 1
            },
            {
                "name": "Buy Tuba Hat",
                "access_rules": [],
                "visibility_rules": [],
                "item_count": 1
            },
            {
                "name": "Buy Ace Of Hearts",
                "access_rules": [],
                "visibility_rules": [],
                "item_count": 1
            },
            {
                "name": "Buy Ace Of Clubs",
                "access_rules": [],
                "visibility_rules": [],
                "item_count": 1
            },
            {
                "name": "Buy Ace Of Diamonds",
                "access_rules": [],
                "visibility_rules": [],
                "item_count": 1
            },
            {
                "name": "Buy Ace Of Spades",
                "access_rules": [],
                "visibility_rules": [],
                "item_count": 1
            },
            {
                "name": "Buy Jimbo",
                "access_rules": [],
                "visibility_rules": [],
                "item_count": 1
            },
            {
                "name": "Buy D4",
                "access_rules": [],
                "visibility_rules": [],
                "item_count": 1
            },
            {
                "name": "Buy D6",
                "access_rules": [],
                "visibility_rules": [],
                "item_count": 1
            },
            {
                "name": "Buy D20",
                "access_rules": [],
                "visibility_rules": [],
                "item_count": 1
            },
            {
                "name": "Buy Fake Coin",
                "access_rules": [],
                "visibility_rules": [],
                "item_count": 1
            }
        ],
        "map_locations": [
            {
                "map": "Buy",
                "x": 344,
                "y": 376,
                "size": 6
            }
        ]
    }
]